weightanalyser/__init__.py
weightanalyser/cli.py
weightanalyser/dataanalyser.py
weightanalyser/datahandeling.py
weightanalyser/main.py
weightanalyser/visualisation.py
weightanalyser-0.2.data/scripts/weightanalyser
weightanalyser-0.2.dist-info/DESCRIPTION.rst
weightanalyser-0.2.dist-info/METADATA
weightanalyser-0.2.dist-info/RECORD
weightanalyser-0.2.dist-info/WHEEL
weightanalyser-0.2.dist-info/metadata.json
weightanalyser-0.2.dist-info/top_level.txt
