Metadata-Version: 2.0
Name: weightanalyser
Version: 0.2
Summary: Analyse your weight in depth
Home-page: https://github.com/finn-christiansen/weightanalyser
Author: Finn Christiansen
Author-email: mail@finnchristiansen.com
License: UNKNOWN
Platform: UNKNOWN
Requires-Dist: matplotlib
Requires-Dist: scipy
